rip_counter.v
module clock_divider(
    input  clk,
    input reset,
    //using reg because we want to make non blocking assignments
    output reg clk_div2,
    output reg clk_div4,
    output reg clk_div8,
    output reg clk_div16
);

initial begin
    clk_div2 = 0;
    clk_div4 = 0;
    clk_div8 = 0;
    clk_div16 = 0;
end
always @(posedge clk)
    clk_div2 <= ~clk_div2;


always @(posedge clk_div2)
    clk_div4 <= ~clk_div4;

always @(posedge clk_div4)
    clk_div8 <= ~clk_div8;


always @(posedge clk_div8)
    clk_div16 <= ~clk_div16;


endmodule

rip_counter_tb.v
module rip_counter_test;
integer i;
reg clk;
reg reset;
wire clk_div2;
wire clk_div4;
wire clk_div8;
wire clk_div16;



clock_divider uut(clk,reset,clk_div2,clk_div4,clk_div8,clk_div16);


initial begin
    $dumpfile("rip_counter.vcd");
    $dumpvars(0,rip_counter_test);
    for (i=0; i < 100; i = i + 1) begin
        #1
        clk = 1;
        #1 
        clk = 0;
        #1
        clk = -1;
    end
    $finish();
end


endmodule

rip_counter.vcd
$date
	Sun Apr 16 01:50:08 2023
$end
$version
	Icarus Verilog
$end
$timescale
	1s
$end
$scope module rip_counter_test $end
$var wire 1 ! clk_div8 $end
$var wire 1 " clk_div4 $end
$var wire 1 # clk_div2 $end
$var wire 1 $ clk_div16 $end
$var reg 1 % clk $end
$var reg 1 & reset $end
$var integer 32 ' i [31:0] $end
$scope module uut $end
$var wire 1 % clk $end
$var wire 1 & reset $end
$var reg 1 $ clk_div16 $end
$var reg 1 # clk_div2 $end
$var reg 1 " clk_div4 $end
$var reg 1 ! clk_div8 $end
$upscope $end
$upscope $end
$enddefinitions $end
#0
$dumpvars
b0 '
x&
x%
0$
0#
0"
0!
$end
#1
1$
1!
1"
1#
1%
#2
0%
#3
0#
b1 '
1%
#5
0%
#6
0"
1#
b10 '
1%
#8
0%
#9
0#
b11 '
1%
#11
0%
#12
0!
1"
1#
b100 '
1%
#14
0%
#15
0#
b101 '
1%
#17
0%
#18
0"
1#
b110 '
1%
#20
0%
#21
0#
b111 '
1%
#23
0%
#24
0$
1!
1"
1#
b1000 '
1%
#26
0%
#27
0#
b1001 '
1%
#29
0%
#30
0"
1#
b1010 '
1%
#32
0%
#33
0#
b1011 '
1%
#35
0%
#36
0!
1"
1#
b1100 '
1%
#38
0%
#39
0#
b1101 '
1%
#41
0%
#42
0"
1#
b1110 '
1%
#44
0%
#45
0#
b1111 '
1%
#47
0%
#48
1$
1!
1"
1#
b10000 '
1%
#50
0%
#51
0#
b10001 '
1%
#53
0%
#54
0"
1#
b10010 '
1%
#56
0%
#57
0#
b10011 '
1%
#59
0%
#60
0!
1"
1#
b10100 '
1%
#62
0%
#63
0#
b10101 '
1%
#65
0%
#66
0"
1#
b10110 '
1%
#68
0%
#69
0#
b10111 '
1%
#71
0%
#72
0$
1!
1"
1#
b11000 '
1%
#74
0%
#75
0#
b11001 '
1%
#77
0%
#78
0"
1#
b11010 '
1%
#80
0%
#81
0#
b11011 '
1%
#83
0%
#84
0!
1"
1#
b11100 '
1%
#86
0%
#87
0#
b11101 '
1%
#89
0%
#90
0"
1#
b11110 '
1%
#92
0%
#93
0#
b11111 '
1%
#95
0%
#96
1$
1!
1"
1#
b100000 '
1%
#98
0%
#99
0#
b100001 '
1%
#101
0%
#102
0"
1#
b100010 '
1%
#104
0%
#105
0#
b100011 '
1%
#107
0%
#108
0!
1"
1#
b100100 '
1%
#110
0%
#111
0#
b100101 '
1%
#113
0%
#114
0"
1#
b100110 '
1%
#116
0%
#117
0#
b100111 '
1%
#119
0%
#120
0$
1!
1"
1#
b101000 '
1%
#122
0%
#123
0#
b101001 '
1%
#125
0%
#126
0"
1#
b101010 '
1%
#128
0%
#129
0#
b101011 '
1%
#131
0%
#132
0!
1"
1#
b101100 '
1%
#134
0%
#135
0#
b101101 '
1%
#137
0%
#138
0"
1#
b101110 '
1%
#140
0%
#141
0#
b101111 '
1%
#143
0%
#144
1$
1!
1"
1#
b110000 '
1%
#146
0%
#147
0#
b110001 '
1%
#149
0%
#150
0"
1#
b110010 '
1%
#152
0%
#153
0#
b110011 '
1%
#155
0%
#156
0!
1"
1#
b110100 '
1%
#158
0%
#159
0#
b110101 '
1%
#161
0%
#162
0"
1#
b110110 '
1%
#164
0%
#165
0#
b110111 '
1%
#167
0%
#168
0$
1!
1"
1#
b111000 '
1%
#170
0%
#171
0#
b111001 '
1%
#173
0%
#174
0"
1#
b111010 '
1%
#176
0%
#177
0#
b111011 '
1%
#179
0%
#180
0!
1"
1#
b111100 '
1%
#182
0%
#183
0#
b111101 '
1%
#185
0%
#186
0"
1#
b111110 '
1%
#188
0%
#189
0#
b111111 '
1%
#191
0%
#192
1$
1!
1"
1#
b1000000 '
1%
#194
0%
#195
0#
b1000001 '
1%
#197
0%
#198
0"
1#
b1000010 '
1%
#200
0%
#201
0#
b1000011 '
1%
#203
0%
#204
0!
1"
1#
b1000100 '
1%
#206
0%
#207
0#
b1000101 '
1%
#209
0%
#210
0"
1#
b1000110 '
1%
#212
0%
#213
0#
b1000111 '
1%
#215
0%
#216
0$
1!
1"
1#
b1001000 '
1%
#218
0%
#219
0#
b1001001 '
1%
#221
0%
#222
0"
1#
b1001010 '
1%
#224
0%
#225
0#
b1001011 '
1%
#227
0%
#228
0!
1"
1#
b1001100 '
1%
#230
0%
#231
0#
b1001101 '
1%
#233
0%
#234
0"
1#
b1001110 '
1%
#236
0%
#237
0#
b1001111 '
1%
#239
0%
#240
1$
1!
1"
1#
b1010000 '
1%
#242
0%
#243
0#
b1010001 '
1%
#245
0%
#246
0"
1#
b1010010 '
1%
#248
0%
#249
0#
b1010011 '
1%
#251
0%
#252
0!
1"
1#
b1010100 '
1%
#254
0%
#255
0#
b1010101 '
1%
#257
0%
#258
0"
1#
b1010110 '
1%
#260
0%
#261
0#
b1010111 '
1%
#263
0%
#264
0$
1!
1"
1#
b1011000 '
1%
#266
0%
#267
0#
b1011001 '
1%
#269
0%
#270
0"
1#
b1011010 '
1%
#272
0%
#273
0#
b1011011 '
1%
#275
0%
#276
0!
1"
1#
b1011100 '
1%
#278
0%
#279
0#
b1011101 '
1%
#281
0%
#282
0"
1#
b1011110 '
1%
#284
0%
#285
0#
b1011111 '
1%
#287
0%
#288
1$
1!
1"
1#
b1100000 '
1%
#290
0%
#291
0#
b1100001 '
1%
#293
0%
#294
0"
1#
b1100010 '
1%
#296
0%
#297
0#
b1100011 '
1%
#299
0%
#300
0!
1"
1#
b1100100 '
1%
